HISTORY.rst
LICENSE.rst
MANIFEST.in
README.rst
setup.py
netsight/__init__.py
netsight.async.egg-info/PKG-INFO
netsight.async.egg-info/SOURCES.txt
netsight.async.egg-info/dependency_links.txt
netsight.async.egg-info/entry_points.txt
netsight.async.egg-info/namespace_packages.txt
netsight.async.egg-info/not-zip-safe
netsight.async.egg-info/requires.txt
netsight.async.egg-info/top_level.txt
netsight/async/__init__.py
netsight/async/config.py
netsight/async/configure.zcml
netsight/async/registry.py
netsight/async/browser/BaseAsyncView.py
netsight/async/browser/__init__.py
netsight/async/browser/configure.zcml
netsight/async/browser/images/spinner.gif
netsight/async/browser/js/processing.js
netsight/async/browser/templates/processing.pt
netsight/async/browser/tests/__init__.py
netsight/async/browser/tests/base.py
netsight/async/browser/tests/test_BaseAsyncView.py
netsight/async/locales/netsight.async.pot
netsight/async/locales/de/LC_MESSAGES/netsight.async.po
netsight/async/locales/en/LC_MESSAGES/netsight.async.po
netsight/async/profiles/default/metadata.xml