Metadata-Version: 1.0
Name: netsight.async
Version: 1.1.1
Summary: Provides a base view for running asynchronous processes from Zope.
Home-page: http://www.netsight.co.uk
Author: Richard Mitchell
Author-email: richard@netsight.co.uk
License: Apache 2.0
Keywords: Plone Zope Asynchronous Fork Process Task Browser View
Platform: UNKNOWN
Classifier: Framework :: Plone
Classifier: Framework :: Zope2
Classifier: Programming Language :: Python
